qfast/instantiation/native/qs.py
qfast_qs-2.0.0.dist-info/LICENSE.txt
qfast_qs-2.0.0.dist-info/METADATA
qfast_qs-2.0.0.dist-info/WHEEL
qfast_qs-2.0.0.dist-info/top_level.txt
qfast_qs-2.0.0.dist-info/RECORD
