Metadata-Version: 2.1
Name: qfast-qs
Version: 2.0.0
Summary: QFAST QSearch Plugin
Home-page: https://github.com/BQSKit/qfast-qs
Author: Ed Younis
Author-email: edyounis@lbl.gov
License: UNKNOWN
Project-URL: Bug Tracker, https://github.com/BQSKit/qfast-qs/issues
Project-URL: Source Code, https://github.com/BQSKit/qfast-qs
Keywords: quantum synthesis compilation
Platform: UNKNOWN
Classifier: Development Status :: 5 - Production/Stable
Classifier: Environment :: Console
Classifier: Intended Audience :: Developers
Classifier: Intended Audience :: Science/Research
Classifier: Operating System :: OS Independent
Classifier: Programming Language :: Other Scripting Engines
Classifier: Programming Language :: Python :: 3 :: Only
Classifier: Programming Language :: Python :: 3.5
Classifier: Programming Language :: Python :: 3.6
Classifier: Programming Language :: Python :: 3.7
Classifier: Topic :: Scientific/Engineering
Classifier: Topic :: Scientific/Engineering :: Mathematics
Classifier: Topic :: Scientific/Engineering :: Physics
Classifier: Topic :: Software Development :: Compilers
Requires-Python: >=3.5, <4
Requires-Dist: qfast (>=2.0.0)
Requires-Dist: qsearch (>=2.0.0a1)
